unitvalue/__init__.py
unitvalue/units.py
dimensioned_values-0.1.1.dist-info/LICENSE
dimensioned_values-0.1.1.dist-info/METADATA
dimensioned_values-0.1.1.dist-info/WHEEL
dimensioned_values-0.1.1.dist-info/top_level.txt
dimensioned_values-0.1.1.dist-info/RECORD
